{
  "$schema": "https://registry.scalar.com/@scalar/schemas/config",
  "scalar": "2.0.0",
  "info": {
    "title": "Dash.fi Internal API Docs",
    "description": "Private OpenAPI reference for Dash.fi's internal-facing REST APIs."
  },
  "siteConfig": {
    "subdomain": "dashfi-internal-api-docs",
    "customDomain": "internal-api-docs.dash.fi",
    "theme": "default",
    "logo": {
      "lightMode": "https://dashbook.vercel.app/api/logo/wordmark/transparent",
      "darkMode": "https://dashbook.vercel.app/api/logo/wordmark/jade-dark"
    }
  },
  "navigation": {
    "routes": {
      "/": {
        "type": "group",
        "title": "Dash.fi Internal API Docs",
        "children": {
          "": {
            "type": "page",
            "title": "Overview",
            "filepath": "docs/index.md"
          },
          "/surface": {
            "type": "group",
            "title": "Surface",
            "children": {
              "/surface/web-api": {
                "type": "openapi",
                "title": "Surface Web API",
                "namespace": "dash-fi",
                "slug": "surface-web-api",
                "version": "latest",
                "mode": "folder"
              },
              "/surface/admin-api": {
                "type": "openapi",
                "title": "Surface Admin API",
                "namespace": "dash-fi",
                "slug": "surface-admin-api",
                "version": "latest",
                "mode": "folder"
              },
              "/surface/internal-api": {
                "type": "openapi",
                "title": "Surface Internal API",
                "namespace": "dash-fi",
                "slug": "surface-internal-api",
                "version": "latest",
                "mode": "folder"
              }
            }
          },
          "/core": {
            "type": "group",
            "title": "Core",
            "children": {
              "/core/account-api": {
                "type": "openapi",
                "title": "Account API",
                "namespace": "dash-fi",
                "slug": "core-account-api",
                "version": "latest",
                "mode": "folder",
                "config": {
                  "baseServerURL": "https://gateway-internal.dash.fi"
                }
              },
              "/core/accounts-payable": {
                "type": "openapi",
                "title": "Accounts Payable API",
                "namespace": "dash-fi",
                "slug": "core-accounts-payable",
                "version": "latest",
                "mode": "folder",
                "config": {
                  "baseServerURL": "https://gateway-external.dash.fi"
                }
              },
              "/core/ad-audit-api": {
                "type": "openapi",
                "title": "Ad Pay Protection Project API",
                "namespace": "dash-fi",
                "slug": "core-ad-audit-api",
                "version": "latest",
                "mode": "folder",
                "config": {
                  "baseServerURL": "https://gateway-external.dash.fi"
                }
              },
              "/core/ad-audit-web-analytics": {
                "type": "openapi",
                "title": "Ad Audit Web Analytics API",
                "namespace": "dash-fi",
                "slug": "core-ad-audit-web-analytics",
                "version": "latest",
                "mode": "folder",
                "config": {
                  "baseServerURL": "https://gateway-external.dash.fi"
                }
              },
              "/core/card-api": {
                "type": "openapi",
                "title": "Card API",
                "namespace": "dash-fi",
                "slug": "core-card-api",
                "version": "latest",
                "mode": "folder",
                "config": {
                  "baseServerURL": "https://gateway-internal.dash.fi"
                }
              },
              "/core/card-share-api": {
                "type": "openapi",
                "title": "Card Share API",
                "namespace": "dash-fi",
                "slug": "core-card-share-api",
                "version": "latest",
                "mode": "folder",
                "config": {
                  "baseServerURL": "https://gateway-external.dash.fi"
                }
              },
              "/core/card-transaction-rule": {
                "type": "openapi",
                "title": "Card transaction rules API",
                "namespace": "dash-fi",
                "slug": "core-card-transaction-rule",
                "version": "latest",
                "mode": "folder",
                "config": {
                  "baseServerURL": "https://gateway-internal.dash.fi"
                }
              },
              "/core/credit-api": {
                "type": "openapi",
                "title": "Credit API",
                "namespace": "dash-fi",
                "slug": "core-credit-api",
                "version": "latest",
                "mode": "folder",
                "config": {
                  "baseServerURL": "https://gateway-internal.dash.fi"
                }
              },
              "/core/credit-cash-advance": {
                "type": "openapi",
                "title": "Credit Cash Advance API",
                "namespace": "dash-fi",
                "slug": "core-credit-cash-advance",
                "version": "latest",
                "mode": "folder",
                "config": {
                  "baseServerURL": "https://gateway-internal.dash.fi"
                }
              },
              "/core/credit-statement": {
                "type": "openapi",
                "title": "Credit Statement API",
                "namespace": "dash-fi",
                "slug": "core-credit-statement",
                "version": "latest",
                "mode": "folder",
                "config": {
                  "baseServerURL": "https://gateway-internal.dash.fi"
                }
              },
              "/core/customer": {
                "type": "openapi",
                "title": "Customer API",
                "namespace": "dash-fi",
                "slug": "core-customer",
                "version": "latest",
                "mode": "folder",
                "config": {
                  "baseServerURL": "https://gateway-internal.dash.fi"
                }
              },
              "/core/fee-main-api": {
                "type": "openapi",
                "title": "Fee API",
                "namespace": "dash-fi",
                "slug": "core-fee-main-api",
                "version": "latest",
                "mode": "folder",
                "config": {
                  "baseServerURL": "https://gateway-internal.dash.fi"
                }
              },
              "/core/integrations-cfx-inbound": {
                "type": "openapi",
                "title": "CFX inbound API",
                "namespace": "dash-fi",
                "slug": "core-integrations-cfx-inbound",
                "version": "latest",
                "mode": "folder",
                "config": {
                  "baseServerURL": "https://gateway-external.dash.fi"
                }
              },
              "/core/integrations-oauth": {
                "type": "openapi",
                "title": "OAuth Integrations API",
                "namespace": "dash-fi",
                "slug": "core-integrations-oauth",
                "version": "latest",
                "mode": "folder",
                "config": {
                  "baseServerURL": "https://gateway-external.dash.fi"
                }
              },
              "/core/integrations-plaid-inbound-webhooks": {
                "type": "openapi",
                "title": "Plaid Inbound Webhooks API",
                "namespace": "dash-fi",
                "slug": "core-integrations-plaid-inbound-webhooks",
                "version": "latest",
                "mode": "folder",
                "config": {
                  "baseServerURL": "https://gateway-external.dash.fi"
                }
              },
              "/core/lead-api": {
                "type": "openapi",
                "title": "Lead API",
                "namespace": "dash-fi",
                "slug": "core-lead-api",
                "version": "latest",
                "mode": "folder",
                "config": {
                  "baseServerURL": "https://gateway-external.dash.fi"
                }
              },
              "/core/partner-api": {
                "type": "openapi",
                "title": "Partner API",
                "namespace": "dash-fi",
                "slug": "core-partner-api",
                "version": "latest",
                "mode": "folder",
                "config": {
                  "baseServerURL": "https://gateway-internal.dash.fi"
                }
              },
              "/core/payable-api": {
                "type": "openapi",
                "title": "Payable API",
                "namespace": "dash-fi",
                "slug": "core-payable-api",
                "version": "latest",
                "mode": "folder",
                "config": {
                  "baseServerURL": "https://gateway-internal.dash.fi"
                }
              },
              "/core/public-api": {
                "type": "openapi",
                "title": "Public Dash.fi API",
                "namespace": "dash-fi",
                "slug": "core-public-api",
                "version": "latest",
                "mode": "folder",
                "config": {
                  "baseServerURL": "https://gateway-external.dash.fi"
                }
              },
              "/core/rewards-lithic-api": {
                "type": "openapi",
                "title": "Lithic Rewards API",
                "namespace": "dash-fi",
                "slug": "core-rewards-lithic-api",
                "version": "latest",
                "mode": "folder",
                "config": {
                  "baseServerURL": "https://gateway-internal.dash.fi"
                }
              },
              "/core/rewards-payouts-api": {
                "type": "openapi",
                "title": "Rewards Payouts API",
                "namespace": "dash-fi",
                "slug": "core-rewards-payouts-api",
                "version": "latest",
                "mode": "folder",
                "config": {
                  "baseServerURL": "https://gateway-internal.dash.fi"
                }
              },
              "/core/rewards-transaction": {
                "type": "openapi",
                "title": "Rewards Transaction API",
                "namespace": "dash-fi",
                "slug": "core-rewards-transaction",
                "version": "latest",
                "mode": "folder",
                "config": {
                  "baseServerURL": "https://gateway-internal.dash.fi"
                }
              },
              "/core/risk-api": {
                "type": "openapi",
                "title": "Risk API",
                "namespace": "dash-fi",
                "slug": "core-risk-api",
                "version": "latest",
                "mode": "folder",
                "config": {
                  "baseServerURL": "https://gateway-external.dash.fi"
                }
              },
              "/core/risk-plaid-webhooks": {
                "type": "openapi",
                "title": "Risk Plaid Webhooks API",
                "namespace": "dash-fi",
                "slug": "core-risk-plaid-webhooks",
                "version": "latest",
                "mode": "folder",
                "config": {
                  "baseServerURL": "https://gateway-internal.dash.fi"
                }
              },
              "/core/transactions-e6-card-back-office": {
                "type": "openapi",
                "title": "EOD card settlement transactions back office API",
                "namespace": "dash-fi",
                "slug": "core-transactions-e6-card-back-office",
                "version": "latest",
                "mode": "folder",
                "config": {
                  "baseServerURL": "https://gateway-internal.dash.fi"
                }
              },
              "/core/transactions-e6-card-main-api": {
                "type": "openapi",
                "title": "Card transactions API",
                "namespace": "dash-fi",
                "slug": "core-transactions-e6-card-main-api",
                "version": "latest",
                "mode": "folder",
                "config": {
                  "baseServerURL": "https://gateway-internal.dash.fi"
                }
              },
              "/core/user-api": {
                "type": "openapi",
                "title": "User API",
                "namespace": "dash-fi",
                "slug": "core-user-api",
                "version": "latest",
                "mode": "folder",
                "config": {
                  "baseServerURL": "https://gateway-internal.dash.fi"
                }
              }
            }
          }
        }
      }
    }
  }
}
